pybindxml/__init__.py
pybindxml/reader.py
pybindxml-0.7.dist-info/DESCRIPTION.rst
pybindxml-0.7.dist-info/METADATA
pybindxml-0.7.dist-info/RECORD
pybindxml-0.7.dist-info/WHEEL
pybindxml-0.7.dist-info/metadata.json
pybindxml-0.7.dist-info/top_level.txt
