Metadata-Version: 2.0
Name: pybindxml
Version: 0.7
Summary: Read ISC BIND's statistics XML for processing.
Home-page: https://github.com/jforman/pybindxml
Author: Jeffrey Forman
Author-email: code@jeffreyforman.net
License: MIT
Platform: UNKNOWN
Requires-Python: >2.7, !=3.3.*
Requires-Dist: beautifulsoup4
